[
  {
    "id": "AeHIrLTr6JkxGE6SN-0Rw",
    "name": "Allen Raymond",
    "email": "nulla.ante@vestibul.co.uk",
    "phone": "(992) 914-3792"
  },
  {
    "id": "drsAJ4SHPYqZeG-83QTVW",
    "name": "Kennedy Lane",
    "email": "mattis.Cras@nonenimMauris.net",
    "phone": "(542) 451-7038"
  },
  {
    "id": "vza2RIzNGIwutCVCs4mCL",
    "name": "Wylie Pope",
    "email": "est@utquamvel.net",
    "phone": "(692) 802-2949"
  },
  {
    "id": "05olLMgyVQdWRwgKfg5J6",
    "name": "Cyrus Jackson",
    "email": "nibh@semsempererat.com",
    "phone": "(501) 472-5218"
  },
  {
    "id": "1DEXoP8AuCGYc1YgoQ6hw",
    "name": "Abbot Franks",
    "email": "scelerisque@magnis.org",
    "phone": "(186) 568-3720"
  },
  {
    "id": "C9sjBfCo4UJCWjzBnOtxl",
    "name": "Simon Morton",
    "email": "dui.Fusce.diam@Donec.com",
    "phone": "(233) 738-2360"
  },
  {
    "id": "e6ywwRe4jcqxXfCZOj_1e",
    "name": "Thomas Lucas",
    "email": "nec@Nulla.com",
    "phone": "(704) 398-7993"
  },
  {
    "id": "rsKkOQUi80UsgVPCcLZZW",
    "name": "Alec Howard",
    "email": "Donec.elementum@scelerisquescelerisquedui.net",
    "phone": "(748) 206-2688"
  },
  {
    "id": "mhqcCz6pNsLPtd2wtGPYR"
  },
  {
    "id": "ISXlk8T24OYL8r-z9LaiN"
  },
  {
    "id": "6ZfR1gZ-So0HvBfxuADKC"
  },
  {
    "id": "_-JM4LsvW1KyCqUt-OiHR"
  },
  {
    "id": "qqoTAtN3aoJh8JJlUxX4-"
  },
  {
    "id": "rejoCI_84TLYGrGqzrY0Y"
  },
  {
    "id": "h1v-DNlzCf29OjubX1AUZ"
  },
  {
    "id": "hi2sH_PuamZlocifS3CE7"
  },
  {
    "id": "qOhgo98Nsa0zKWKp1MFq1"
  },
  {
    "id": "42B95gKhcGv-RMup6llxb"
  },
  {
    "id": "Ub067GoZBzRCSkCPDoYTL"
  },
  {
    "id": "SuvEWqHlkw-P9I2yyihEJ"
  },
  {
    "id": "3QL4Edleg1O0OUntrV2Yo"
  },
  {
    "id": "jn7KB4GNjgafMIzDzvcfG"
  },
  {
    "id": "DDv9stpygOykW_-C8minC"
  },
  {
    "id": "doA-aUu98f1hGA5o5oFem"
  },
  {
    "id": "ghFKA2JBc-g4OilNzPX1t"
  },
  {
    "id": "6_y5k58qYyIaEoxmvXV8j"
  },
  {
    "id": "nxucA9JKNwzRfAOSs07xu"
  },
  {
    "id": "kBqqKZ8f2jBqBUYVzYBki"
  },
  {
    "id": "qLSYU9vACcUzM4C_GdHww"
  },
  {
    "id": "DWUaB8xGH0XFz1OYeuIel"
  },
  {
    "id": "A6AcTlhFeTvG7Cq1trB30"
  },
  {
    "id": "_9SzqKDiUH2vM6i1DxfKh"
  },
  {
    "id": "XeGixArh5m68CUaJ0c29q"
  },
  {
    "id": "qet9Sk1PrB48-gqLBa7l2"
  },
  {
    "id": "xYiPT87RFGSU5UF_OrOKs"
  },
  {
    "id": "uEjNntI1QtgGpSnZfxXK1"
  },
  {
    "id": "0lAVhacHQFwBlVWHySAD1"
  },
  {
    "id": "dbXhM7qUaqPrSgLs8nUfo"
  },
  {
    "id": "timswCQZjHkVGOxu0-bUM"
  },
  {
    "id": "3C18HGpI-d5JHYkTG2IoZ"
  },
  {
    "id": "H7j4wviJWGKrK67SlXfSJ"
  },
  {
    "id": "uiZ5TU936gG0ZJ6igapr0"
  },
  {
    "id": "62iI9mTzr_Dabu4wD9NxR"
  },
  {
    "id": "v8IKBSBlBh0vn9VVZUaZK"
  },
  {
    "id": "Yhuau49rJiGC3nEcIizqV"
  },
  {
    "id": "_IM1df37WFjzLR4TC_LmM"
  },
  {
    "id": "kq0JkT6A2vzTB60cNOReY"
  },
  {
    "id": "4MqxuIoMAEJXe7EC0_5xo"
  },
  {
    "id": "OrCqmtN-Ga9yhZrAsnaQu"
  },
  {
    "id": "KWO_Wsl01LEler0Or8Ut0"
  },
  {
    "id": "Sx8ehIOyMedrRKBMJ1YN2"
  },
  {
    "id": "smQuG1g0VgfVc6NruIaL4"
  },
  {
    "id": "banIsVP2pjbEaVUgJcaDh"
  },
  {
    "id": "aCUsZ0caoJuFGRVx-fiZo"
  },
  {
    "id": "31Fz8xEdqcm87oo7QVlaj"
  },
  {
    "id": "NqZeKF9jXyMcIcvJQjdHL"
  },
  {
    "id": "Ep0QkMoYCPW3PD3OKwWYK"
  },
  {
    "id": "FnyREkCaIgTvgbKeDIqzp"
  },
  {
    "id": "pwoJsgLMNDJ1E3HUNki8u"
  },
  {
    "id": "4TJlcIoTo_5aJy-gC-uzy"
  },
  {
    "id": "qpRV5iZw5l6UbTgVpTlYM"
  },
  {
    "id": "vXkfK5OA9phljFGICgDE5"
  },
  {
    "id": "BFDWD1QyO7waS79GDWrnu"
  },
  {
    "id": "5M7YRkqUw1Sus5XkK9GVd"
  },
  {
    "id": "C8OuSJsvoNjEXy6_CAPYT"
  },
  {
    "id": "uHgjSD2Y9HCnq7ziqALwH"
  },
  {
    "id": "pEIPi_QNiQvkkF2HJ64xc"
  },
  {
    "id": "HJy8pOpNBz7TuVpESwH5q"
  },
  {
    "id": "rTvlFBpupsAxhDId-IHeh"
  },
  {
    "id": "Rl-qwq2G-7DRpdlsKu2Wh"
  },
  {
    "id": "0soa3eNYEK_OAdOobFzdX"
  },
  {
    "id": "ZamN7YEBGLL8VkizPOJa-"
  },
  {
    "id": "xhze8_D-7Re963klg1jDP"
  },
  {
    "id": "jVhKoQgFgovfjkGCwxkAO"
  },
  {
    "id": "wzr6exRfEr5dyLdczah8e"
  },
  {
    "id": "E_9AE0X_DWsswKyHlkYsy"
  },
  {
    "id": "1KpGPKbfVIKYTQA88dGKb"
  },
  {
    "id": "Lb0_tHFk9pa0d-dO2gLI6"
  },
  {
    "id": "O5JfKpEHGlhPIL9uEB5PD"
  },
  {
    "id": "RaS7uhviXzOU6F1zOkkx_"
  },
  {
    "id": "9ms21RkIsPVeHQ0KznFpK"
  },
  {
    "id": "itQCaoHkgkhLzBr4nLw30"
  },
  {
    "id": "mF5XQrPhQmYnI9q4tp-KR"
  },
  {
    "id": "-CjcD8Hg2w_TfXNZl8qut"
  },
  {
    "id": "09lbtvnHfLD1f01AmbtWb"
  },
  {
    "id": "1Z_cjdkrpIBljKbK9qhVk"
  },
  {
    "id": "MHctCvU6IIx-jI7nWTIWq"
  },
  {
    "id": "gwXuWqNlnO0jqsEdmHMQC"
  },
  {
    "id": "tj2IWQqkVnKMywXwKZc_2"
  },
  {
    "id": "zY9OqOZ0yr7O08TWCPfY3",
    "name": "Mango",
    "email": "mango@gmail.com",
    "phone": "322-22-22"
  }
]